xcalculator/__init__.py
xcalculator/calculator.py
xcalculator/main.py
xcalculator-0.9.3.dist-info/METADATA
xcalculator-0.9.3.dist-info/WHEEL
xcalculator-0.9.3.dist-info/entry_points.txt
xcalculator-0.9.3.dist-info/licenses/LICENSE
xcalculator-0.9.3.dist-info/RECORD
