Metadata-Version: 2.3
Name: xcalculator
Version: 0.9.3
Summary: Cross-platform calculator
Project-URL: Homepage, https://github.com/jacob-thompson/xcalculator
Project-URL: Bug Reports, https://github.com/jacob-thompson/xcalculator/issues
Author-email: "Jacob A. Thompson" <jacobalthompson@gmail.com>
Maintainer-email: "Jacob A. Thompson" <jacobalthompson@gmail.com>
License: MIT License
Keywords: application,arithmetic,calculator,cross,easy,executable,math,mathematics,platform,simple,tkinter,xplatform
Classifier: Development Status :: 3 - Alpha
Classifier: License :: OSI Approved :: MIT License
Classifier: Programming Language :: Python :: 3
Classifier: Programming Language :: Python :: 3 :: Only
Classifier: Programming Language :: Python :: 3.7
Classifier: Programming Language :: Python :: 3.8
Classifier: Programming Language :: Python :: 3.9
Classifier: Programming Language :: Python :: 3.10
Classifier: Programming Language :: Python :: 3.11
Classifier: Programming Language :: Python :: 3.12
Classifier: Programming Language :: Python :: 3.13
Classifier: Topic :: Games/Entertainment
Requires-Python: >=3.2
Requires-Dist: sympy
